postilion/__init__.py
postilion/company.py
postilion/filing.py
postilion/financial.py
postilion-0.0.4.dist-info/LICENSE
postilion-0.0.4.dist-info/METADATA
postilion-0.0.4.dist-info/WHEEL
postilion-0.0.4.dist-info/top_level.txt
postilion-0.0.4.dist-info/RECORD
