Metadata-Version: 2.1
Name: postilion
Version: 0.0.4
Summary: A wrapper around the postiliion api
Home-page: https://github.com/terranblake/pypostilion
Author: Terran Blake
Author-email: terranblake@gmail.com
License: MIT
Download-URL: https://github.com/terranblake/pypostilion/releases/download/0.0.4/postilion-0.4.tar.gz
Keywords: financial,modeling,postilion,python,api,wrapper,financial-modeling,clean,spicy
Platform: UNKNOWN
Classifier: Development Status :: 3 - Alpha
Classifier: Intended Audience :: Developers
Classifier: Topic :: Software Development :: Build Tools
Classifier: License :: OSI Approved :: MIT License
Classifier: Programming Language :: Python :: 3
Classifier: Programming Language :: Python :: 3.4
Classifier: Programming Language :: Python :: 3.5
Classifier: Programming Language :: Python :: 3.6
Classifier: Natural Language :: English
Classifier: Topic :: Office/Business :: Financial
Classifier: Topic :: Office/Business
Classifier: Topic :: Office/Business :: Financial :: Accounting
Classifier: Topic :: Office/Business :: Financial :: Investment
Classifier: Topic :: Office/Business :: Financial :: Spreadsheet
Classifier: Topic :: Software Development :: Libraries
Classifier: Topic :: Software Development :: Libraries :: Python Modules
Requires-Dist: requests
